wisp.py
wisp/__init__.py
wisp/wisp.py
wisp-0.0.8b0.dist-info/LICENSE
wisp-0.0.8b0.dist-info/METADATA
wisp-0.0.8b0.dist-info/WHEEL
wisp-0.0.8b0.dist-info/top_level.txt
wisp-0.0.8b0.dist-info/RECORD
