Metadata-Version: 2.1
Name: wisp
Version: 0.0.8b0
Summary: A preference based location finder application
Home-page: https://github.com/Jimut123/wisp
Author: Jimut Bahan Pal
Author-email: jimutbahanpal@yahoo.com
License: UNKNOWN
Platform: UNKNOWN
Classifier: Programming Language :: Python :: 3
Classifier: License :: OSI Approved :: MIT License
Classifier: Operating System :: OS Independent
Requires-Dist: requests
Requires-Dist: pandas
Requires-Dist: folium
Requires-Dist: geopy
Requires-Dist: numpy
Requires-Dist: wget
Requires-Dist: datetime
Requires-Dist: IPython
Requires-Dist: pip
